{
  "components": {
    "walletAuth": {
      "connect": "Poveži novčanik"
    },
    "banners": {
      "dalgona": {
        "title": "Rezbarite Dalgona za Zaradu",
        "description": "Pridružite se izazovima rezanja slatkiša i osvojite DAL nagrade.",
        "cta": "Igraj sada"
      }
    },
    "pollOfTheWeek": {
      "previousPolls": "Prethodne ankete",
      "vote": "Glasaj sada"
    },
    "stakeForm": {
      "deposit": "Depozit",
      "withdraw": "Povuci",
      "balance": "Stanje:",
      "depositPlaceholder": "Iznos za depozit",
      "withdrawPlaceholder": "Iznos za povlačenje",
      "max": "Maksimalno",
      "interest": "Kamata:",
      "collect": "Prikupi",
      "depositButton": "Položi drahme",
      "withdrawButton": "Povuci drahme"
    },
    "toasts": {
      "wallet": {
        "connectInWorldApp": "Molimo otvorite ovu aplikaciju u World App-u za povezivanje novčanika.",
        "stakingError": "Greška pri ulaganju tokena",
        "withdrawError": "Greška pri povlačenju tokena",
        "collectError": "Greška pri prikupljanju nagrada"
      },
      "referral": {
        "pendingReward": "Obrada nagrade na čekanju za {{username}}...",
        "rewardSuccess": "Uspješno nagrađen {{username}}!",
        "sendingReward": "Slanje nagrade od 50 WDD korisniku {{username}}..."
      },
      "basicIncome": {
        "setupSuccess": "Temeljni Dohodak Plus aktiviran! Sada pripremamo nagradu za {{username}}...",
        "setupWithReferrer": "Prvo postavljamo Temeljni Dohodak Plus, zatim ćemo nagraditi {{username}}...",
        "error": "Greška pri aktivaciji Temeljnog Dohotka",
        "errorPlus": "Greška pri aktivaciji Temeljnog Dohotka Plus"
      },
      "transaction": {
        "error": "Došlo je do neočekivane greške",
        "errorClaim": "Došlo je do neočekivane greške prilikom preuzimanja"
      }
    },
    "comingSoonDrawer": {
      "title": "Uskoro dostupno",
      "description": "Ova značajka je trenutno u razvoju. Ostanite uz nas!"
    },
    "tabSwiper": {
      "tabs": {
        "politicalParties": "Stranke",
        "polls": "Ankete",
        "openLetters": "Otvorena pisma",
        "elections": "Izbori",
        "referendums": "Referendumi"
      }
    },
    "politicalPartyList": {
      "myParty": "Moja stranka",
      "createParty": "Stvori Novu Stranku",
      "noParty": "Još niste stvorili niti se pridružili stranci.",
      "discover": "Otkrij",
      "partyDetails": "Detalji stranke",
      "description": "Opis",
      "partyInfo": "Informacije o stranci",
      "leader": "Vođa",
      "website": "Web stranica",
      "members": "Članovi",
      "noMembers": "Još nema članova",
      "approvalNote": "Stranke s funkcionalnom službenom poveznicom i/ili rastućim članstvom imaju prednost pri odobravanju.",
      "bannedMembers": "Zabranjeni članovi",
      "errorLoading": "Pogreška pri učitavanju stranke",
      "partyNotFound": "Stranka nije pronađena",
      "partyNotFoundDescription": "Stranka koju tražite ne postoji ili je uklonjena.",
      "backToParties": "Natrag na stranke",
      "joining": "Pridruživanje...",
      "joinParty": "Pridruži se stranci",
      "shareParty": "Podijeli stranku",
      "copied": "Poveznica kopirana u međuspremnik",
      "status": {
        "pending": "Na čekanju",
        "active": "Aktivna",
        "inactive": "Neaktivna"
      },
      "tabs": {
        "top": "Najbolje",
        "trending": "U trendu",
        "new": "Novo",
        "pending": "Na čekanju"
      },
      "emptyState": {
        "pending": "Nema stranaka na čekanju.",
        "noParties": "Nema dostupnih stranaka za pridruživanje."
      },
      "partyCard": {
        "pending": "Na čekanju",
        "deleted": "Izbrisano",
        "members": "članova",
        "actions": {
          "leaveParty": "Napusti stranku",
          "joinParty": "Pridruži se stranci",
          "joinPendingParty": "Pridruži se stranci na čekanju"
        },
        "management": {
          "title": "Upravljanje Strankom",
          "manageMembers": "Upravljanje članovima",
          "updateInfo": "Ažuriraj informacije",
          "transferLeadership": "Prijenos vodstva",
          "deleteParty": "Izbriši stranku"
        }
      },
      "drawers": {
        "create": {
          "title": "Stvori Novu Stranku",
          "name": {
            "label": "Ime stranke",
            "placeholder": "Unesite ime stranke",
            "error": "Molimo unesite ime stranke"
          },
          "shortName": {
            "label": "Skraćeno ime",
            "placeholder": "Unesite skraćeno ime ili akronim",
            "error": "Molimo unesite skraćeno ime"
          },
          "description": {
            "label": "Opis",
            "placeholder": "Unesite opis stranke",
            "error": "Molimo unesite opis"
          },
          "officialLink": {
            "label": "Službena poveznica",
            "placeholder": "Unesite službenu web stranicu ili društveni link (neobavezno)"
          },
          "limitWarning": {
            "approaching": "Približavate se ograničenju znakova: {{current}}/{{max}}",
            "reached": "Dosegnuto je maksimalno ograničenje znakova"
          },
          "button": {
            "creating": "Stvaranje...",
            "create": "Stvori stranku"
          }
        },
        "update": {
          "title": "Ažuriraj Informacije o Stranci",
          "button": {
            "update": "Ažuriraj",
            "updateDescription": "Ažuriraj opis"
          }
        },
        "transferLeadership": {
          "title": "Prijenos Vodstva",
          "description": "Unesite adresu lisnice novog vođe ili pretražite po korisničkom imenu. Adresa mora biti postojećeg člana stranke.",
          "lookup": {
            "label": "Pretraži po korisničkom imenu",
            "placeholder": "Unesite korisničko ime World App-a",
            "buttonText": "Pretraži",
            "loading": "Pretraživanje...",
            "foundUser": "Pronađen korisnik: ",
            "address": "Adresa: "
          },
          "newLeader": {
            "label": "Adresa novog vođe",
            "placeholder": "Unesite adresu lisnice (0x...)",
            "errors": {
              "required": "Molimo unesite adresu",
              "invalid": "Molimo unesite valjanu Ethereum adresu (0x...)"
            }
          },
          "button": {
            "processing": "Obrada...",
            "transfer": "Prijenos vodstva"
          }
        },
        "leave": {
          "title": "Napusti Trenutnu Stranku",
          "description": "Već ste član stranke {{partyName}}. Morate napustiti vašu trenutnu stranku prije nego što se pridružite novoj.",
          "leaderWarning": "Napomena: Trenutno ste vođa ove stranke. Ako napustite, vodstvo će biti izgubljeno ili ponovno dodijeljeno sistemom.",
          "button": {
            "leaving": "Napuštanje...",
            "leave": "Napusti {{partyShortName}}"
          }
        },
        "createConfirm": {
          "title": "Napusti Trenutnu Stranku",
          "description": "Već ste član stranke {{partyName}}. Morate napustiti vašu trenutnu stranku prije nego što stvorite novu.",
          "leaderWarning": "Napomena: Trenutno ste vođa ove stranke. Ako napustite, vodstvo će biti izgubljeno ili ponovno dodijeljeno sistemom.",
          "button": {
            "processing": "Obrada...",
            "leaveAndCreate": "Napusti {{partyShortName}} i stvori"
          }
        },
        "delete": {
          "title": "Izbriši Stranku",
          "confirmPending": "Jeste li sigurni da želite izbrisati ovu stranku na čekanju?",
          "confirm": "Jeste li sigurni da želite izbrisati ovu stranku?",
          "button": {
            "processing": "Obrada...",
            "deletePending": "Izbriši stranku na čekanju",
            "delete": "Izbriši stranku"
          }
        },
        "memberManagement": {
          "title": "Upravljanje Članovima",
          "label": "Adresa člana",
          "tabs": {
            "remove": "Ukloni",
            "ban": "Zabrani",
            "unban": "Ukini zabranu"
          },
          "remove": {
            "description": "Unesite adresu lisnice člana kojeg želite ukloniti ili pretražite po korisničkom imenu.",
            "button": {
              "processing": "Obrada...",
              "remove": "Ukloni člana"
            }
          },
          "ban": {
            "description": "Unesite korisničko ime ili adresu lisnice člana kojeg želite zabraniti iz stranke.",
            "button": {
              "processing": "Obrada...",
              "ban": "Zabrani člana"
            }
          },
          "unban": {
            "description": "Unesite korisničko ime ili adresu lisnice zabranjenog člana kojeg želite ponovno dopustiti u stranku.",
            "button": {
              "processing": "Obrada...",
              "unban": "Ukini zabranu člana"
            }
          }
        }
      }
    }
  },
  "pages": {
    "earn": {
      "title": "Zarada",
      "tabs": {
        "basicIncome": {
          "tabTitle": "Temeljni dohodak",
          "title": "Temeljni Dohodak",
          "subtitle": "Prijavite se za preuzimanje temeljnog dohotka",
          "setupSubtitle": "Postavite svoj temeljni dohodak",
          "claimableSubtitle": "Dostupne drahme",
          "claimableTooltip1": "Kao dio našeg",
          "claimableTooltip2": "programa otkupa",
          "claimableTooltip3": ", usavršavamo razine temeljnog dohotka kako bismo stvorili održive, dugoročne koristi za našu zajednicu. Molimo pogledajte",
          "claimableTooltip4": "FAQ",
          "claimableTooltip5": "za trenutne stope.",
          "activateButton": "Aktiviraj Temeljni Dohodak",
          "claimButton": "Preuzmi",
          "plus": {
            "title": "Temeljni Dohodak Plus",
            "newBadge": "Novo",
            "drawerTrigger": "Predstavljamo Temeljni Dohodak Plus",
            "subtitle": "Dodatni prihod za verificirane korisnike",
            "drawer": {
              "title": "Temeljni Dohodak Plus",
              "subtitle": "Dodatni prihod za verificirane korisnike",
              "features": {
                "rate": {
                  "title": "0,19 WDD dodatnih po danu"
                },
                "verification": {
                  "title": "Ekskluzivno za Orb-verificirane korisnike radi osiguranja pravedne distribucije"
                }
              },
              "activateButton": "Aktiviraj Temeljni Dohodak Plus",
              "claimButton": "Preuzmi Temeljni Dohodak Plus",
              "claimBasicButton": "Preuzmi Temeljni Dohodak"
            }
          }
        },
        "savings": {
          "tabTitle": "Štednja",
          "title": "Štedni Račun",
          "subtitle": "Zaradite kamatu svake sekunde",
          "tooltip": "Osnovna stopa od 69% GPR. Prikupljajte i reinvestirajte kamatu za postizanje blizu 100% efektivnog godišnjeg prinosa. Povucite sredstva bilo kada."
        },
        "invite": {
          "title": "Pozovi",
          "subtitle": "Zaradi 10 WDD po prijatelju koji se pridruži",
          "tooltip": "Prijatelji se moraju pridružiti našoj novoj web aplikaciji.",
          "learnMore": "Saznaj više",
          "stats": {
            "title": "Vaše statistike preporuka",
            "invites": "Prihvaćeni pozivi",
            "rewards": "Ukupne nagrade"
          },
          "actions": {
            "copyLink": "Kopiraj referentni link",
            "copied": "Referentni link kopiran u međuspremnik!",
            "connectWallet": "Molimo povežite novčanik za generiranje referentnog linka",
            "share": "Podijeli link pozivnice"
          },
          "share": {
            "title": "Pridružite se Svjetskoj Republici",
            "text": "Koristite moju pozivnicu da se pridružite Svjetskoj Republici i zajedno zaradite nagrade!"
          }
        },
        "contribute": {
          "title": "Doprinesi",
          "subtitle": "Uključi se, budi nagrađen",
          "buybackProgram": {
            "topnav": "Program Otkupa",
            "title": "Program Otkupa Tokena",
            "subtitle": "Zajedno ojačajmo vrijednost WDD-a",
            "sections": {
              "fundingSources": {
                "title": "Izvori financiranja",
                "devRewards": {
                  "title": "World Dev Nagrade",
                  "weekProgress": "Tjedan 7 od 12"
                },
                "worldRetro": {
                  "title": "World Retro Financiranje"
                },
                "optimism": {
                  "title": "Optimism Retro Financiranje"
                },
                "affiliate": {
                  "title": "Partnerske provizije"
                }
              },
              "commitment": {
                "title": "Naša obveza od 50%",
                "description": "Obvezujemo se koristiti najmanje 50% naših nagrada iz programa za otkup WDD-a.",
                "viewAccount": "Pogledaj račun za otkup"
              },
              "valueCycle": {
                "title": "Pozitivan Ciklus Vrijednosti",
                "steps": {
                  "step1": "Više korisnika i korištenja aplikacije",
                  "step2": "Veće nagrade",
                  "step3": "Više otkupa tokena"
                }
              },
              "helpSection": {
                "title": "Kako možete pomoći",
                "intro": "Možete izravno doprinijeti povećanju vrijednosti vaših WDD tokena:",
                "steps": {
                  "invite": {
                    "title": "Pozovite druge da se pridruže",
                    "description": "Proširite našu zajednicu provjerenih članova"
                  },
                  "useApp": {
                    "title": "Redovito koristite aplikaciju",
                    "description": "Potaknite pozitivan ekonomski ciklus"
                  }
                }
              }
            },
            "actions": {
              "share": "Podijelite pozivnicu"
            },
            "cta": "Pogledajte nagrade mini aplikacije"
          },
          "buybackLink": {
            "title": "Program otkupa",
            "description": "Rast vrijednosti WDD-a pokretan zajednicom"
          },
          "partySubsidy": {
            "topnav": "Program Subvencija",
            "title": "Program Subvencija za Stranke",
            "subtitle": "Izgradite svoj politički pokret i zaradite",
            "weeklyPool": {
              "old": "100.000",
              "new": "250.000 WDD",
              "subtitle": "Fiksni fond"
            },
            "devRewards": {
              "title": "10% naših Dev Nagrada",
              "subtitle": "Varijabilni fond",
              "tooltip": "World distribuira nagrade za developere na temelju korištenja aplikacije od strane verificiranih ljudi.",
              "checkOutRewards": "Pogledajte nagrade"
            },
            "howItWorks": {
              "title": "Kako to funkcionira",
              "steps": {
                "createParty": {
                  "title": "Stvorite stranku",
                  "description": "Pokrenite svoj politički pokret u aplikaciji World Republic"
                },
                "growMembership": {
                  "title": "Dospite na glasački listić",
                  "description": "Povećajte svoje članstvo kako biste se kvalificirali za tjedne izbore"
                },
                "earnRewards": {
                  "title": "Primite financiranje",
                  "description": "Zaradite subvencije proporcionalne glasovima koje vaša stranka dobije"
                }
              }
            },
            "cta": {
              "createJoin": "Stvorite ili se pridružite stranci",
              "leaderGroup": "Pridružite se grupi vođa stranke"
            },
            "payouts": {
              "title": "Isplate",
              "week": "Tjedan",
              "showAll": "Prikaži sve"
            }
          }
        }
      }
    },
    "govern": {
      "title": "Upravljanje",
      "tabs": {
        "polls": "Ankete",
        "openLetters": "Otvorena pisma",
        "elections": "Izbori",
        "referendums": "Referendumi"
      },
      "sections": {
        "polls": {
          "title": "Anketa Tjedna",
          "description": "Brza glasovanja o aktualnim temama",
          "previous": {
            "title": "Prethodne Ankete",
            "backToGovern": "Natrag na Upravljanje",
            "polls": {
              "digitalGovernance": "S obzirom na brzi napredak umjetne inteligencije i digitalnih tehnologija, trebaju li nacije kolektivno osigurati odgovoran razvoj i upravljanje kako bi se spriječili široko rasprostranjeni društveni poremećaji?",
              "nuclearEscalationRisk": "Treba li uspostaviti globalni okvir za smanjenje rizika od nuklearne eskalacije u regijama s povišenim geopolitičkim napetostima?",
              "nuclearDisarmamentTalks": "S obzirom na nedavna izvješća o povećanoj proizvodnji nuklearnog materijala, trebaju li svjetske sile ponovno pokrenuti sveobuhvatne pregovore o razoružanju?",
              "pandemicPreparednessFund": "Treba li uspostaviti trajni globalni fond za osiguravanje kontinuiranog i pravednog pristupa resursima za buduću pripravnost i odgovor na pandemije diljem svijeta?",
              "globalAidCuts": "Trebaju li zemlje preispitati smanjenja vanjske pomoći koja riskiraju poništavanje desetljeća napretka u borbi protiv bolesti poput AIDS-a i malarije?",
              "coralCrisisAction": "Trebaju li se države obvezati na koordiniranu globalnu strategiju za zaštitu koraljnih grebena usred najgoreg događaja izbjeljivanja koralja u zabilježenoj povijesti?",
              "aiSafetyTreaty": "Trebaju li države pristati na provedivi globalni sporazum o sigurnosti umjetne inteligencije?",
              "heatAdaptation": "Trebaju li zemlje uspostaviti globalni koordinacijski mehanizam za rana upozorenja na toplinske valove i zajedničke napore pomoći kako bi se zaštitile ranjive populacije tijekom ekstremnih vrućina?",
              "globalMilitaryExerciseProtocol": "Trebaju li se zemlje složiti oko međunarodnog protokola za obavještavanje i promatranje velikih vojnih vježbi u blizini spornih regija kako bi se smanjio rizik od eskalacije?",
              "globalMaritimeSecurity": "Bi li trebala biti uspostavljena međunarodna radna skupina za pomorsku sigurnost kako bi se zaštitili trgovački brodovi u međunarodnim vodama od oružanih napada?",
              "globalNuclearDialogue": "Bi li velike sile trebale biti obvezane međunarodnim sporazumom na kontinuirane nuklearne pregovore na razini stručnjaka s protivničkim državama kako bi se spriječila eskalacija i osigurao diplomatski nadzor?",
              "globalMiningStandards": "Bi li trebalo uspostaviti međunarodni protokol kako bi se osiguralo ekološki i društveno odgovorno rudarenje kritičnih minerala potrebnih za tehnologije čiste energije?",
              "globalIMFQuotaReform": "Treba li revidirati formulu za pregled kvota MMF-a kako bi se povećala glasačka moć ekonomija u razvoju i osiguralo pravednije donošenje odluka?",
              "globalEnergyTransition": "Trebaju li zemlje usvojiti pravno obvezujući globalni okvir za ubrzanje prijelaza s fosilnih goriva na obnovljive izvore energije?",
              "globalTradeArbitration": "Treba li uspostaviti obvezujući međunarodni arbitražni panel za rješavanje trgovinskih sporova i osiguravanje transparentnih, predvidljivih carinskih politika?",
              "geoengineeringRegulation": "Trebaju li države stvoriti namjenski globalni fond za ubrzanje obnove šuma velikih razmjera kao ključnu strategiju za ublažavanje klimatskih promjena?",
              "globalFoodWaste": "Trebaju li vlade provoditi stroge mjere za smanjenje bacanja hrane, poput poreznih olakšica za donacije hrane i kazni za pretjerano odbacivanje jestive hrane?",
              "globalClimateFinance": "Trebaju li razvijene zemlje značajno povećati klimatsko financiranje kako bi pomogle zemljama u razvoju suočiti se s utjecajima klimatskih promjena i podržale prijelaz na tehnologije s niskim emisijama ugljika?",
              "globalEduEquity": "Treba li postojati koordinirani globalni napor za premošćivanje digitalnog jaza osiguravanjem jednakog pristupa digitalnim alatima za učenje i pristupačnom internetu za učenike diljem svijeta?",
              "oilTariffImpact": "Treba li težiti globalnim sporazumima za ograničavanje ekstremnih carinskih mjera na izvoz nafte i plina kako bi se stabiliziralo međunarodno energetsko tržište?",
              "agiExistentialRisk": "Trebaju li svjetski čelnici pregovarati o obvezujućem međunarodnom sporazumu za ublažavanje potencijalnih egzistencijalnih rizika koje predstavlja umjetna opća inteligencija?",
              "biodiversityFinance": "Treba li stvoriti namjenski globalni fond za mobiliziranje ulaganja u očuvanje prirode kako bi se ispunili ambiciozni ciljevi zaštite biološke raznolikosti?",
              "supplyChainResilience": "Trebaju li države surađivati kako bi uspostavile globalni okvir za jačanje otpornosti opskrbnih lanaca usred kontinuiranih poremećaja?",
              "digitalInclusion": "Treba li postojati globalna inicijativa za premošćivanje digitalnog jaza i osiguravanje jednakog pristupa digitalnim tehnologijama diljem svijeta?",
              "techTransparency": "Trebaju li globalne tehnološke tvrtke biti obvezne usvojiti transparentne politike odlučivanja kako bi zaštitile povjerenje javnosti?",
              "disasterRelief": "Treba li uspostaviti globalni fond za brzi odgovor kako bi se pružila trenutna pomoć za razorne prirodne katastrofe poput velikih potresa?",
              "aiWatermarking": "Trebaju li globalni propisi zahtijevati obvezno označavanje vodenim žigom sadržaja generiranog umjetnom inteligencijom kako bi se suzbilo dezinformiranje u izborima i medijima?",
              "biotech": "Treba li postojati globalni regulatorni okvir za nove biotehnologije kako bi se osigurala njihova etička uporaba i sigurnost?",
              "spaceMilitarization": "Trebaju li se globalni čelnici dogovoriti o protokolima za sprječavanje militarizacije svemira i osiguravanje njegove miroljubive uporabe?",
              "dataSovereignty": "Trebaju li se provesti međunarodne smjernice za zaštitu globalno generiranih podataka pod jedinstvenim okvirom digitalne suverenosti?",
              "fourDayWeek": "Podržavate li rastući globalni pokret prema četverodnevnom radnom tjednu kao standardnom modelu zapošljavanja?",
              "nuclearSecurity": "Trebaju li se uspostaviti obvezujući međunarodni sporazumi za osiguranje nuklearnih postrojenja u zonama sukoba?",
              "aviationResilience": "Je li međunarodna zrakoplovna infrastruktura dovoljno otporna za rukovanje neočekivanim velikim poremećajima?",
              "waterResources": "Trebaju li države stvoriti okvir suradnje za upravljanje zajedničkim vodnim resursima usred rastućeg globalnog nedostatka vode?",
              "maternalHealth": "Treba li uspostaviti namjensku globalnu zdravstvenu rezervu pomoći za zaštitu zdravlja majki i djece tijekom zamrzavanja međunarodne pomoći?",
              "marsMission": "Podržavate li suradnju država na zajedničkoj misiji u duboki svemir prema Marsu?",
              "globalRecession": "Mislite li da trenutni globalni ekonomski trendovi ukazuju na rizik od sinkronizirane recesije među velikim ekonomijama?",
              "aidCorridors": "Trebaju li sve zone sukoba s humanitarnim krizama civilnog stanovništva automatski pokrenuti međunarodno koordinirane koridore pomoći?",
              "nationalSovereignty": "Podržavate li globalne političke okvire koji uravnotežuju nacionalni suverenitet s koordiniranim odgovorima na zajedničke izazove?",
              "climateDisasters": "Trebaju li zemlje koje doživljavaju ekstremne vremenske katastrofe (npr. požari, poplave) dobiti prioritetnu financijsku pomoć iz globalnog klimatskog fonda?",
              "aiSafety": "Trebaju li globalni UI developeri biti obvezni pauzirati treniranje modela snažnijih od trenutnih sustava dok se ne uspostave međunarodni sigurnosni sporazumi?",
              "corporateTax": "Trebaju li korporacije koje posluju u više zemalja biti podložne jedinstvenom globalnom minimalnom poreznom stopom radi smanjenjenja nejednakosti?",
              "spaceDebris": "Slažete li se da bi svemirske nacije i korporacije trebale biti zakonski obvezne ukloniti neaktivne satelite kako bi se smanjio orbitalni otpad?",
              "digitalPrivacy": "Mislite li da je stvaranje univerzalnih standarda digitalne privatnosti ključno za zaštitu individualnih prava u sve povezanijem svijetu?",
              "nuclearProliferation": "Vjerujete li da postojeće globalne mjere učinkovito smanjuju rizik od nuklearne proliferacije?",
              "cybersecurity": "Jesu li trenutne međunarodne mjere kibernetičke sigurnosti dovoljne za zaštitu kritične globalne infrastrukture od rastućih cyber prijetnji?",
              "globalAlliances": "Mislite li da će brza preraspodjela globalnih saveza dovesti do sigurnijeg međunarodnog poretka?",
              "climateResilience": "Je li trenutni globalni pristup klimatskoj otpornosti dovoljan za suočavanje s povećanom učestalošću ekstremnih vremenskih događaja?",
              "tradeTariffs": "Mislite li da će rastući trend uvođenja carina među velikim ekonomijama značajno narušiti globalnu trgovinsku stabilnost?",
              "diseaseManagement": "Jeste li uvjereni u sposobnost svijeta da spriječi i upravlja novim zaraznim bolestima?",
              "aiRegulation": "Trebaju li se uspostaviti obvezujući međunarodni propisi za upravljanje etičkim razvojem umjetne inteligencije?",
              "spaceRegulation": "Trebaju li postojati obvezni međunarodni sporazumi za ograničavanje svemirskog otpada od satelita i raketa?",
              "diplomaticDialogue": "Vjerujete li da održivi diplomatski dijalog među svjetskim čelnicima može pomoći smanjiti globalne napetosti?",
              "migration": "Trebaju li bogate zemlje prihvatiti više migranata koji bježe od sukoba ili klimatskih katastrofa?",
              "rareEarths": "Treba li dati prioritet međunarodnoj suradnji na rijetkim zemljanim mineralima radi poboljšanja globalne sigurnosti resursa?",
              "cryptocurrency": "Trebaju li globalne vlasti uspostaviti jedinstvene standarde za regulaciju kriptovaluta i suzbijanje financijskog kriminala?",
              "disinformation": "Mislite li da bi trebalo implementirati globalne mjere za suzbijanje širenja dezinformacija na internetu?",
              "diseaseOutbreaks": "Trebaju li zemlje biti obvezne dijeliti podatke u stvarnom vremenu tijekom izbijanja bolesti kako bi se spriječile globalne zdravstvene krize?",
              "militaryIntervention": "Trebaju li zemlje s naprednim vojnim sposobnostima intervenirati za deeskalaciju sukoba u regijama koje doživljavaju iznenadne izbijanje rata?",
              "aiDevelopment": "Trebaju li vlade dati prioritet regulaciji razvoja umjetne inteligencije (UI) kako bi spriječile zlouporabu, čak i ako to usporava inovacije?",
              "asteroidDefense": "Vjerujete li da bi vlade širom svijeta trebale povećati financiranje za praćenje svemira i istraživanje skretanja asteroida?",
              "peaceNegotiations": "Trebaju li velike sile koje pregovaraju o mirovnim sporazumima biti obvezne uključiti zemlje izravno pogođene sukobom?",
              "taiwanPolicy": "Trebaju li Sjedinjene Države zadržati svoju politiku 'strateške dvosmislenosti' o Tajvanu kako bi izbjegle eskalaciju napetosti s Kinom?",
              "quakeCodes": "Treba li globalni građevinski propisi biti standardizirani kako bi se poboljšala otpornost na potrese u gradskoj infrastrukturi?",
              "foodSecurity": "Treba li implementirati globalni okvir za jačanje sigurnosti hrane u svjetlu klimatskih promjena i geopolitičke nestabilnosti?",
              "eWasteRegulation": "Treba li postojati globalni regulatorni okvir za upravljanje elektroničkim otpadom i ublažavanje njegovog utjecaja na okoliš?",
              "oceanHealth": "Treba li implementirati globalni okvir za zaštitu i obnovu svjetskih oceana od onečišćenja, prekomjernog ribolova i utjecaja klimatskih promjena?",
              "fairTechCompetition": "Trebaju li globalne tehnološke tvrtke biti obvezne pridržavati se standardiziranih pravila kako bi se osiguralo pošteno tržišno natjecanje u sektoru umjetne inteligencije i širim tehnološkim industrijama te spriječila zlouporaba tržišta?",
              "globalVaccineEquity": "Treba li uspostaviti međunarodno koordinirani okvir kako bi se osigurao ravnopravan pristup cjepivima i osnovnim lijekovima tijekom globalnih zdravstvenih kriza?",
              "globalDigitalServicesTax": "Trebaju li države usvojiti koordinirani porez na digitalne usluge usmjeren na prihode velikih tehnoloških platformi kako bi se osiguralo pravedno i predvidljivo globalno oporezivanje?",
              "sovereignDebtRestructuring": "Bi li trebao postojati međunarodno koordinirani mehanizam za restrukturiranje državnog duga kako bi se pružila pravovremena pomoć zemljama koje se suočavaju s neodrživim razinama duga?",
              "wildlifeTrafficking": "Trebaju li države surađivati na posebnom međunarodnom okviru za borbu protiv ilegalnog trgovanja divljim životinjama, uključujući nove oblike biopiratstva insekata i drugih vrsta?",
              "criticalMineralsExport": "Treba li postojati međunarodno koordinirani okvir za kontrolu izvoza kritičnih minerala—poput rijetkih zemlji i strateških metala—kako bi se spriječili šokovi u lancima opskrbe i geopolitička prisila?",
              "tradePolicyStability": "Bi li nacije trebale usvojiti koordinirani međunarodni kodeks ponašanja za tarifne politike kako bi se poboljšala predvidljivost i stabilnost u globalnoj trgovini?",
              "cyberResilienceProtocol": "Treba li države uspostaviti koordinirani globalni protokol za kibernetičku sigurnost kako bi se obranile od AI-potaknutih kibernetičkih napada koji bi mogli poremetiti ključnu infrastrukturu diljem svijeta?",
              "middleEastEscalation": "Treba li neovisni konzorcij nacija podržati neutralnu inicijativu za deeskalaciju na Bliskom istoku kako bi se smanjio rizik od regionalnog sukoba?"
            }
          }
        },
        "openLetters": {
          "title": "Otvorena Pisma",
          "description": "Javne izjave donositeljima odluka",
          "addNew": "Dodaj svoje otvoreno pismo",
          "statements": {
            "aiRisk": {
              "title": "Izjava o UI Riziku",
              "referenceTitle": "Centar za UI sigurnost"
            },
            "nuclear": {
              "title": "UN-ovo Otvoreno Pismo o Zabrani Nuklearnog Oružja",
              "referenceTitle": "Institut za budućnost života"
            },
            "autonomousWeapons": {
              "title": "Zavjet o Smrtonosnom Autonomnom Oružju",
              "referenceTitle": "Institut za budućnost života"
            },
            "longView": {
              "title": "Otvoreno Pismo koje poziva svjetske čelnike da pokažu Dugoročno Vodstvo o Egzistencijalnim Prijetnjama",
              "referenceTitle": "Institut za budućnost života"
            }
          }
        },
        "elections": {
          "title": "Izbori",
          "description": "Izaberite svoje predstavnike",
          "testElections": {
            "title": "Probni Izbori",
            "description": "Pomozite nam distribuirati stranačke subvencije i poboljšati naš sustav upravljanja",
            "button": "Otvori probne izbore"
          },
          "currentElectionPage": {
            "title": "Trenutni izbori",
            "testElectionTitle": "Testni izbori",
            "testElectionSubtitle": "Pomozite nam testirati naš sustav glasanja",
            "testElectionTooltip1": "Za više informacija, pročitajte ",
            "testElectionTooltip2": "FAQ o izborima",
            "testElectionTooltip3": ".",
            "politicalParties": "Političke stranke",
            "searchPlaceholder": "Pretražite stranke...",
            "leaderPrefix": "Vođa: ",
            "noActiveElection": "Nema aktivnih izbora",
            "noActiveElectionDescription": "Trenutno nema aktivnih izbora",
            "backToOverview": "Povratak na pregled",
            "buttons": {
              "voted": "Glasano",
              "vote": "Glasaj",
              "processing": "Obrađuje se...",
              "cancel": "Otkaži"
            },
            "confirmation": {
              "vote": {
                "title": "Potvrdite svoj glas",
                "description": "Upravo ćete dati svoj glas za {{partyName}}. Ova će radnja biti zabilježena na blockchainu.",
                "confirmText": "Potvrdi glas"
              },
              "change": {
                "title": "Promijenite svoj glas",
                "description": "Jeste li sigurni da želite promijeniti svoj glas s {{previousPartyName}} na {{partyName}}?",
                "confirmText": "Potvrdi promjenu"
              },
              "remove": {
                "title": "Uklonite svoj glas",
                "description": "Jeste li sigurni da želite ukloniti svoj glas za {{partyName}}? Nećete glasati ni za jednu stranku.",
                "confirmText": "Da, ukloni glas"
              }
            },
            "toasts": {
              "connectInWorldApp": "Molimo otvorite ovu aplikaciju u aplikaciji World kako biste glasali.",
              "connectWallet": "Molimo prvo povežite svoj novčanik.",
              "noCurrentElection": "Nije moguće utvrditi trenutne izbore.",
              "fetchStatusError": "Dohvaćanje statusa glasanja nije uspjelo. Molimo pokušajte ponovo.",
              "transactionFailed": "Transakcija nije uspjela ili je odbijena.",
              "voteRemovedSuccess": "Glas je uspješno uklonjen",
              "voteSuccess": "Uspješno ste glasali za {{partyName}}!",
              "voteError": "Došlo je do pogreške prilikom davanja vašeg glasa."
            },
            "electionFaqPage": {
              "title": "FAQ o izborima",
              "items": {
                "electionPurpose": {
                  "question": "Koja je svrha ovih izbora?",
                  "answer": "Ovi izbori su ključni dio našeg modela upravljanja. U početku određuju kako se distribuiraju stranačke subvencije, nagrađujući stranke na temelju podrške koju dobiju. Kako naš sustav sazrijeva, rezultati izbora davat će strankama značajnije odgovornosti. Ovo je iterativni proces koji nam pomaže da učimo i napredujemo."
                },
                "ballotQualification": {
                  "question": "Kako stranka dospije na glasački listić?",
                  "answer": "Da bi bila na glasačkom listiću, stranka mora imati članove koji čine najmanje 0,05% ukupnog broja primatelja Basic Income Plus. To osigurava da stranke imaju temeljnu razinu podrške od aktivnih, provjerenih članova."
                },
                "howToVote": {
                  "question": "Kako glasati?",
                  "answer": "Na stranici za izbore možete vidjeti popis političkih stranaka koje ispunjavaju uvjete. Jednostavno dodirnite gumb 'Glasaj' pored stranke koju želite podržati. Od vas će se tražiti da potvrdite svoj glas putem svog novčanika."
                },
                "canIChangeVote": {
                  "question": "Mogu li promijeniti svoj glas?",
                  "answer": "Da, možete promijeniti svoj glas u bilo kojem trenutku dok su izbori aktivni. Jednostavno glasajte za drugu stranku i vaš prethodni glas bit će zamijenjen. Također možete u potpunosti ukloniti svoj glas."
                },
                "electionDeadline": {
                  "question": "Kada završavaju izbori?",
                  "answer": "Probni izbori traju do nedjelje u 23:59:59 UTC. Glasovi se moraju dati prije tog vremena kako bi se ubrojili za trenutne izbore."
                },
                "isVoteAnonymous": {
                  "question": "Je li moj glas anoniman?",
                  "answer": "Glasanje je pseudonimno. Iako je vaš glas povezan s adresom vašeg novčanika na blockchainu radi transparentnosti, vaš stvarni identitet nije izravno vezan uz njega."
                },
                "whatArePartySubsidies": {
                  "question": "Što su stranačke subvencije?",
                  "answer": "Stranačke subvencije su nagrade koje se distribuiraju političkim strankama na temelju glasova koje dobiju. Ovaj program financira stranačke aktivnosti i pomaže im u rastu. Možete saznati više o <a href=\"/{{lang}}/earn/contribute/party-subsidy\" class=\"font-medium text-gray-900 underline\">Programu stranačkih subvencija</a>."
                }
              }
            }
          }
        },
        "referendums": {
          "title": "Referendumi",
          "description": "Izravna glasanja o važnim pitanjima",
          "worldConstitutional": {
            "title": "Svjetski Ustavni Referendum",
            "description": "Sudjelujte u povijesnom glasanju o načelima koja će voditi kolektivnu budućnost čovječanstva",
            "button": "Uskoro"
          }
        },
        "politicalParties": {
          "title": "Političke Stranke",
          "description": "Ujedinite se globalno oko zajedničkih vrijednosti"
        }
      }
    },
    "menu": {
      "title": "Izbornik",
      "sections": {
        "experimental": {
          "title": "POSTAVKE",
          "links": {
            "language": "Jezik"
          }
        },
        "connect": {
          "title": "POVEZIVANJE",
          "links": {
            "community": "Zajednica",
            "announcements": "Obavijesti",
            "x": "X"
          }
        },
        "help": {
          "title": "POMOĆ",
          "links": {
            "support": "Podrška",
            "faq": "FAQ"
          }
        },
        "code": {
          "title": "KÔD",
          "links": {
            "app": "Aplikacija",
            "contracts": "Pametni ugovori"
          }
        }
      }
    },
    "faq": {
      "title": "Česta Pitanja",
      "items": {
        "appPurpose": {
          "question": "Što je Svjetska Republika?",
          "answer": "Svjetska Republika je otvorena, demokratska organizacija posvećena rješavanju najhitnijih globalnih izazova čovječanstva. Pruža okvir za kolektivno donošenje odluka o pitanjima koja se mogu učinkovito riješiti samo na globalnoj razini, poput UI rizika, klimatskih promjena ili biosigurnosti."
        },
        "basicIncome": {
          "question": "Što je Temeljni dohodak?",
          "answer": "Naš Temeljni dohodak je dnevna subvencija od 0,01 WDD (svjetska drahma) koja se pruža svim građanima Svjetske Republike. Akumulira se u stvarnom vremenu i može se preuzeti u bilo kojem trenutku putem aplikacije."
        },
        "basicIncomePlus": {
          "question": "Kako aktivirati Temeljni dohodak Plus?",
          "answer": "Temeljni dohodak Plus pruža dodatnih 0,19 WDD dnevno i dostupan je isključivo Orb-verificiranim korisnicima. Nakon aktivacije Temeljnog dohotka, vidjet ćete opciju za aktivaciju Temeljnog dohotka Plus na stranici Zarada."
        },
        "savings": {
          "question": "Kako funkcionira Štedni račun?",
          "answer": "Štedni račun vam omogućuje polaganje WDD tokena i zaradu godišnje kamate od 69%. Kroz stalno reinvestiranje zarađene kamate, korisnici mogu postići efektivne prinose blizu 100% godišnje, maksimizirajući rast svojih WDD-a tijekom vremena. Kamata se akumulira kontinuirano i može se povući ili reinvestirati u bilo kojem trenutku."
        },
        "referralCodes": {
          "question": "Kako funkcioniraju preporučiteljski kodovi?",
          "answer": "Kao građanin Svjetske Republike, možete zaraditi nagrade kroz naš program preporuka. Podijelite svoju jedinstvenu preporučiteljsku poveznicu s prijateljima i dobit ćete 10 WDD za svaku osobu koja se pridruži našoj web aplikaciji i dovrši provjeru živosti."
        },
        "drachmaValue": {
          "question": "Odakle drahma dobiva svoju vrijednost?",
          "answer": "Drahma dobiva svoju vrijednost kao službena valuta Svjetske Republike. Kako naša demokratska platforma globalnog upravljanja raste, WDD ima potencijal postati značajno sredstvo razmjene u svjetskoj ekonomiji i mogao bi eventualno igrati ulogu u pravednoj raspodjeli koristi od tehnoloških napredaka i globalnih resursa."
        },
        "topWallets": {
          "question": "Tko kontrolira najveće račune?",
          "answer": "Tri najveća računa su <a href='https://worldscan.org/address/0xa3C2c8CE6Be1C55401b5F1EfB6112A86F6374429' target='_blank' rel='noopener noreferrer' class='underline'>Trezor Svjetske Republike</a>, <a href='https://worldscan.org/address/0x02c3B99D986ef1612bAC63d4004fa79714D00012' target='_blank' rel='noopener noreferrer' class='underline'>Fond za osnovni dohodak</a> i <a href='https://worldscan.org/address/0x52DFEe61180A0BCEBe007E5a9Cfd466948aCCA46' target='_blank' rel='noopener noreferrer' class='underline'>Fond za osnovni dohodak plus</a>. Trenutačno ih upravlja osnivač projekta kako bi se osigurala stabilnost dok postupno prenosimo kontrolu na zajednicu. Ostale ključne adrese uključuju <a href='https://worldscan.org/address/0x234302Db10A54BDc11094A8Ef816B0Eaa5FCE3f7' target='_blank' rel='noopener noreferrer' class='underline'>ugovor o štednom računu</a>, <a href='https://worldscan.org/address/0x372dCA057682994568be074E75a03Ced3dD9E60d' target='_blank' rel='noopener noreferrer' class='underline'>distributera nagrada za preporuke</a> i bazene likvidnosti: <a href='https://worldscan.org/address/0xaaEF72194E42aF8f641e90c3e48a7F01e9547097' target='_blank' rel='noopener noreferrer' class='underline'>WLD/WDD</a>, <a href='https://worldscan.org/address/0x24Cda46262Ee6b777416997c52FE140A0B3f6FeA' target='_blank' rel='noopener noreferrer' class='underline'>USDC/WDD</a> i <a href='https://worldscan.org/address/0x3226d525Bb0EA2346D512215ca8df7d81801786E' target='_blank' rel='noopener noreferrer' class='underline'>ETH/WDD</a>."
        },
        "voteRequirements": {
          "question": "Kako mogu sudjelovati u upravljanju?",
          "answer": "Možete sudjelovati pridruživanjem ili stvaranjem političke stranke. Iako su trenutni glasovi ilustrativni, stranke su temelj našeg modela upravljanja. Kako se stranke budu profesionalizirale, otključavat će sve značajnija područja za demokratsku kontrolu, dajući vam glas u našim kolektivnim odlukama."
        }
      }
    },
    "language": {
      "title": "Jezik",
      "options": {
        "english": "English",
        "spanish": "Español",
        "croatian": "Hrvatski"
      }
    }
  }
}
