{
  "components": {
    "walletAuth": {
      "connect": "Подключить кошелек"
    },
    "banners": {
      "dalgona": {
        "title": "Зарабатывайте WDD в 1-м сезоне",
        "description": "Более 1 миллиона наград в 10 тестовых выборах. Без верификации.",
        "cta": "Начать"
      }
    },
    "stakeForm": {
      "deposit": "Внести",
      "withdraw": "Вывести",
      "balance": "Баланс:",
      "depositPlaceholder": "Сумма для внесения",
      "withdrawPlaceholder": "Сумма для вывода",
      "max": "Макс",
      "interest": "Проценты:",
      "collect": "Собрать",
      "depositButton": "Внести драхмы",
      "withdrawButton": "Вывести драхмы"
    },
    "toasts": {
      "wallet": {
        "connectInWorldApp": "Пожалуйста, откройте это приложение в World App для подключения кошелька.",
        "stakingError": "Ошибка при стейкинге токенов",
        "withdrawError": "Ошибка при выводе токенов",
        "collectError": "Ошибка при сборе наград"
      },
      "referral": {
        "pendingReward": "Обработка ожидающей награды для {{username}}...",
        "rewardSuccess": "Успешно награждён {{username}}!",
        "sendingReward": "Отправка награды в 50 WDD пользователю {{username}}..."
      },
      "basicIncome": {
        "setupSuccess": "Базовый доход Плюс активирован! Подготовка награды для {{username}}...",
        "setupWithReferrer": "Сначала настраиваем Базовый доход Плюс, затем наградим {{username}}...",
        "error": "Ошибка при активации Базового дохода",
        "errorPlus": "Ошибка при активации Базового дохода Плюс"
      },
      "transaction": {
        "error": "Произошла непредвиденная ошибка",
        "errorClaim": "Произошла непредвиденная ошибка при получении"
      }
    },
    "tabSwiper": {
      "tabs": {
        "openLetters": "Открытые письма",
        "elections": "Выборы",
        "referendums": "Референдумы"
      }
    }
  },
  "pages": {
    "earn": {
      "title": "Заработок",
      "tabs": {
        "basicIncome": {
          "tabTitle": "Базовый доход",
          "title": "Базовый доход",
          "subtitle": "Войдите, чтобы получить базовый доход",
          "setupSubtitle": "Настройте ваш базовый доход",
          "claimableSubtitle": "Доступные драхмы",
          "claimableTooltip1": "В рамках нашей",
          "claimableTooltip2": "программы выкупа",
          "claimableTooltip3": ", мы настраиваем уровни базового дохода для создания устойчивых, долгосрочных преимуществ для нашего сообщества. Пожалуйста, обратитесь к",
          "claimableTooltip4": "FAQ",
          "claimableTooltip5": "для текущих ставок.",
          "activateButton": "Активировать базовый доход",
          "claimButton": "Получить",
          "plus": {
            "title": "Базовый доход Плюс",
            "newBadge": "Новое",
            "drawerTrigger": "Представляем Базовый доход Плюс",
            "subtitle": "Дополнительный доход для верифицированных пользователей",
            "drawer": {
              "title": "Базовый доход Плюс",
              "subtitle": "Дополнительный доход для верифицированных пользователей",
              "features": {
                "rate": {
                  "title": "Дополнительные 0,0475 WDD в день"
                },
                "verification": {
                  "title": "Эксклюзивно для пользователей, верифицированных через Orb, для обеспечения справедливого распределения"
                }
              },
              "activateButton": "Активировать Базовый доход Плюс",
              "claimButton": "Получить Базовый доход Плюс",
              "claimBasicButton": "Получить Базовый доход"
            }
          }
        },
        "savings": {
          "tabTitle": "Сбережения",
          "title": "Сберегательный счёт",
          "subtitle": "Получайте проценты каждую секунду",
          "tooltip": "Базовая ставка 69% годовых. Собирайте и реинвестируйте проценты для достижения близких к 100% эффективных годовых доходов. Вывод средств доступен в любое время."
        },
        "invite": {
          "title": "Пригласить",
          "subtitle": "Получайте по 10 WDD за каждого друга, который присоединится",
          "tooltip": "Друзья должны присоединиться к нашему новому веб‑приложению.",
          "learnMore": "Узнать больше",
          "stats": {
            "title": "Ваша статистика рефералов",
            "invites": "Принято приглашений",
            "rewards": "Всего наград"
          },
          "actions": {
            "copyLink": "Копировать реферальную ссылку",
            "copied": "Реферальная ссылка скопирована в буфер обмена!",
            "connectWallet": "Пожалуйста, подключите кошелек для создания реферальной ссылки",
            "share": "Поделиться ссылкой-приглашением"
          },
          "share": {
            "title": "Присоединяйтесь к Всемирной Республике",
            "text": "Используйте мою пригласительную ссылку, чтобы присоединиться к Всемирной Республике и вместе получать награды!"
          }
        },
        "contribute": {
          "title": "Участвовать",
          "subtitle": "Участвуйте и получайте награды",
          "buybackProgram": {
            "topnav": "Программа Выкупа",
            "title": "Программа Выкупа Токенов",
            "subtitle": "Усилим ценность WDD вместе",
            "sections": {
              "fundingSources": {
                "title": "Источники финансирования",
                "devRewards": {
                  "title": "Награды Разработчиков World",
                  "weekProgress": "Неделя 7 из 12"
                },
                "worldRetro": {
                  "title": "Финансирование World Retro"
                },
                "optimism": {
                  "title": "Финансирование Optimism Retro"
                },
                "affiliate": {
                  "title": "Партнерские комиссии"
                }
              },
              "commitment": {
                "title": "Наше обязательство",
                "description": "Мы обязуемся использовать не менее 50% всех этих средств для выкупа WDD.",
                "viewAccount": "Посмотреть счет выкупа"
              },
              "valueCycle": {
                "title": "Позитивный Цикл Ценности",
                "steps": {
                  "step1": "Больше пользователей и использование приложения",
                  "step2": "Выше награды",
                  "step3": "Больше выкупа токенов"
                }
              },
              "helpSection": {
                "title": "Как вы можете помочь",
                "intro": "Вы можете напрямую способствовать увеличению стоимости ваших токенов WDD:",
                "steps": {
                  "invite": {
                    "title": "Пригласить других присоединиться",
                    "description": "Расширить наше сообщество проверенных участников"
                  },
                  "useApp": {
                    "title": "Регулярно использовать приложение",
                    "description": "Стимулировать позитивный экономический цикл"
                  }
                }
              }
            },
            "actions": {
              "share": "Поделиться приглашением"
            },
            "cta": "Посмотреть награды мини-приложения"
          },
          "buybackLink": {
            "title": "Программа выкупа",
            "description": "Рост стоимости WDD, движимый сообществом"
          },
          "partySubsidy": {
            "topnav": "Программа субсидий",
            "title": "Программа субсидий для партий",
            "subtitle": "Создайте свое политическое движение и зарабатывайте",
            "weeklyPool": {
              "old": "100 000",
              "new": "250 000 WDD",
              "subtitle": "Фиксированный фонд"
            },
            "devRewards": {
              "title": "10% от наших наград разработчикам",
              "subtitle": "Переменный фонд",
              "tooltip": "World распределяет награды разработчикам на основе использования приложения верифицированными людьми.",
              "checkOutRewards": "Проверить награды"
            },
            "howItWorks": {
              "title": "Как это работает",
              "steps": {
                "createParty": {
                  "title": "Создайте партию",
                  "description": "Начните свое политическое движение в приложении World Republic"
                },
                "growMembership": {
                  "title": "Попасть в бюллетень",
                  "description": "Увеличивайте число своих членов, чтобы получить право на участие в еженедельных выборах"
                },
                "earnRewards": {
                  "title": "Получить финансирование",
                  "description": "Получайте субсидии, пропорциональные голосам, полученным вашей партией"
                }
              }
            },
            "cta": {
              "createJoin": "Создать партию или присоединиться",
              "leaderGroup": "Присоединиться к группе лидеров партии"
            },
            "payouts": {
              "title": "Выплаты",
              "week": "Неделя",
              "showAll": "Показать все"
            }
          }
        }
      }
    },
    "govern": {
      "title": "Управление",
      "tabs": {
        "openLetters": "Открытые письма",
        "elections": "Выборы",
        "referendums": "Референдумы"
      },
      "sections": {
        "openLetters": {
          "title": "Открытые письма",
          "description": "Публичные обращения к лицам, принимающим решения",
          "statements": {
            "aiRisk": {
              "title": "Заявление о рисках ИИ",
              "referenceTitle": "Центр безопасности ИИ"
            },
            "nuclear": {
              "title": "Открытое письмо о запрете ядерного оружия ООН",
              "referenceTitle": "Институт будущего жизни"
            },
            "autonomousWeapons": {
              "title": "Обязательство по автономному летальному оружию",
              "referenceTitle": "Институт будущего жизни"
            },
            "longView": {
              "title": "Открытое письмо, призывающее мировых лидеров проявить дальновидное руководство в отношении экзистенциальных угроз",
              "referenceTitle": "Институт будущего жизни"
            }
          }
        },
        "elections": {
          "title": "Выборы",
          "description": "Выберите своих представителей",
          "testElections": {
            "title": "Тестовые выборы",
            "description": "Помогите нам распределить партийные субсидии и улучшить нашу систему управления",
            "button": "Голосовать"
          }
        },
        "referendums": {
          "title": "Референдумы",
          "description": "Прямое голосование по важным вопросам",
          "worldConstitutional": {
            "title": "Всемирный Конституционный Референдум",
            "description": "Примите участие в историческом голосовании по принципам, которые будут определять коллективное будущее человечества",
            "button": "Скоро"
          }
        }
      }
    },
    "menu": {
      "title": "Меню",
      "sections": {
        "experimental": {
          "title": "НАСТРОЙКИ",
          "links": {
            "language": "Язык"
          }
        },
        "connect": {
          "title": "СВЯЗЬ",
          "links": {
            "community": "Сообщество",
            "announcements": "Объявления",
            "x": "X"
          }
        },
        "help": {
          "title": "ПОМОЩЬ",
          "links": {
            "support": "Сообщество помощи",
            "faq": "FAQ"
          }
        },
        "code": {
          "title": "КОД",
          "links": {
            "app": "Приложение",
            "contracts": "Смарт-контракты"
          }
        }
      }
    },
    "faq": {
      "title": "ЧАВО",
      "items": {
        "appPurpose": {
          "question": "Что такое Всемирная Республика?",
          "answer": "Всемирная Республика — это открытая, демократическая организация, посвященная решению наиболее острых глобальных проблем человечества. Она предоставляет основу для коллективного принятия решений по вопросам, которые могут быть эффективно решены только на глобальном уровне, таким как риски ИИ, изменение климата или биобезопасность."
        },
        "basicIncome": {
          "question": "Что такое базовый доход?",
          "answer": "Наш базовый доход — это ежедневная субсидия в размере 0,0025 WDD (мировая драхма), которая предоставляется всем гражданам Всемирной Республики. Она накапливается в реальном времени и может быть получена в любой момент через приложение."
        },
        "basicIncomePlus": {
          "question": "Как активировать Базовый доход Плюс?",
          "answer": "Базовый доход Плюс предоставляет дополнительные 0,0475 WDD в день и доступен исключительно пользователям, верифицированным через Orb. После активации базового дохода вы увидите опцию активации Базового дохода Плюс на странице Заработка."
        },
        "savings": {
          "question": "Как работает сберегательный счёт?",
          "answer": "Сберегательный счёт позволяет вам вносить токены WDD и получать 69% годовых. Благодаря постоянному реинвестированию заработанных процентов, пользователи могут достичь эффективной доходности близкой к 100% годовых, максимизируя рост своих WDD со временем. Проценты накапливаются непрерывно и могут быть выведены или реинвестированы в любое время."
        },
        "referralCodes": {
          "question": "Как работают реферальные коды?",
          "answer": "Как гражданин Всемирной Республики вы можете получать вознаграждения через нашу реферальную программу. Поделитесь своей уникальной реферальной ссылкой с друзьями, и вы получите 10 WDD за каждого человека, который присоединится к нашему веб‑приложению и пройдёт проверку живости (liveness)."
        },
        "drachmaValue": {
          "question": "Откуда драхма получает свою ценность?",
          "answer": "Драхма получает свою ценность от того, что является официальной валютой Всемирной Республики. По мере роста нашей демократической платформы глобального управления, WDD имеет потенциал стать значимым средством обмена в мировой экономике и в конечном итоге может сыграть роль в справедливом распределении выгод от технологических достижений и глобальных ресурсов."
        },
        "topWallets": {
          "question": "Кто контролирует самые большие счета?",
          "answer": "Три самых крупных счета — это <a href='https://worldscan.org/address/0xa3C2c8CE6Be1C55401b5F1EfB6112A86F6374429' target='_blank' rel='noopener noreferrer' class='underline'>Казначейство Мировой Республики</a>, <a href='https://worldscan.org/address/0x02c3B99D986ef1612bAC63d4004fa79714D00012' target='_blank' rel='noopener noreferrer' class='underline'>Фонд базового дохода</a> и <a href='https://worldscan.org/address/0x52DFEe61180A0BCEBe007E5a9Cfd466948aCCA46' target='_blank' rel='noopener noreferrer' class='underline'>Фонд базового дохода Плюс</a>. В настоящее время они находятся под управлением основателя проекта для обеспечения стабильности, пока мы постепенно передаем контроль сообществу. Другие ключевые адреса включают <a href='https://worldscan.org/address/0x234302Db10A54BDc11094A8Ef816B0Eaa5FCE3f7' target='_blank' rel='noopener noreferrer' class='underline'>договор сберегательного счета</a>, <a href='https://worldscan.org/address/0x372dCA057682994568be074E75a03Ced3dD9E60d' target='_blank' rel='noopener noreferrer' class='underline'>дистрибьютора реферальных вознаграждений</a> и пулы ликвидности: <a href='https://worldscan.org/address/0xaaEF72194E42aF8f641e90c3e48a7F01e9547097' target='_blank' rel='noopener noreferrer' class='underline'>WLD/WDD</a>, <a href='https://worldscan.org/address/0x24Cda46262Ee6b777416997c52FE140A0B3f6FeA' target='_blank' rel='noopener noreferrer' class='underline'>USDC/WDD</a> и <a href='https://worldscan.org/address/0x3226d525Bb0EA2346D512215ca8df7d81801786E' target='_blank' rel='noopener noreferrer' class='underline'>ETH/WDD</a>."
        },
        "voteRequirements": {
          "question": "Как я могу участвовать в управлении?",
          "answer": "Вы можете участвовать, присоединившись к политической партии или создав ее. Хотя текущие голосования являются иллюстративными, партии являются основой нашей модели управления. По мере того как партии будут становиться более профессиональными, они будут открывать все более значимые области для демократического контроля, давая вам право голоса в наших коллективных решениях."
        }
      }
    },
    "language": {
      "title": "Язык",
      "options": {
        "english": "English",
        "spanish": "Español"
      }
    }
  }
}
